pybsd/__init__.py
pybsd/systems/__init__.py
pybsd/systems/handlers.py
pybsd/systems/common.py
PyBSD-0.0.2.dist-info/METADATA
PyBSD-0.0.2.dist-info/DESCRIPTION.rst
PyBSD-0.0.2.dist-info/WHEEL
PyBSD-0.0.2.dist-info/RECORD
PyBSD-0.0.2.dist-info/top_level.txt
PyBSD-0.0.2.dist-info/pbr.json
PyBSD-0.0.2.dist-info/metadata.json
