Metadata-Version: 2.0
Name: PyBSD
Version: 0.0.2
Summary: a Python tool to provision, keep in sync and manage FreeBSD boxes and jails
Home-page: https://github.com/rebost/pybsd
Author: Matías Pizarro
Author-email: matias@pizarro.net
License: BSD
Keywords: FreeBSD,jails,provisioning,ansible,fabric,ezjail,python
Platform: UNKNOWN
Classifier: Development Status :: 2 - Pre-Alpha
Classifier: Environment :: Console
Classifier: Environment :: Other Environment
Classifier: Environment :: Web Environment
Classifier: Intended Audience :: Developers
Classifier: Intended Audience :: System Administrators
Classifier: License :: OSI Approved :: BSD License
Classifier: Operating System :: OS Independent
Classifier: Programming Language :: Python
Classifier: Programming Language :: Python :: 2
Classifier: Programming Language :: Python :: 2.7
Classifier: Programming Language :: Python :: 3
Classifier: Programming Language :: Python :: 3.4
Classifier: Programming Language :: Unix Shell
Classifier: Topic :: System :: Installation/Setup
Classifier: Topic :: System :: Monitoring
Classifier: Topic :: System :: Systems Administration
Requires-Dist: lazy
Requires-Dist: six
Requires-Dist: sortedcontainers
Requires-Dist: Unipath
Requires-Dist: py2-ipaddress
